bibblio/__init__.py
bibblio/admin.py
bibblio/api.py
bibblio/apps.py
bibblio/datastructures.py
bibblio/importer.py
bibblio/models.py
bibblio/registration.py
bibblio/settings.py
bibblio/tests.py
bibblio/management/__init__.py
bibblio/management/commands/__init__.py
bibblio/management/commands/import_bibblio_dump.py
bibblio/migrations/0001_initial.py
bibblio/migrations/0002_remove_catalog_id_field.py
bibblio/migrations/__init__.py
bibblio/static/bibblio/relevancebar.css
bibblio/templates/admin/bibblio/relevancebar.html
bibblio/templates/bibblio/placeholder.txt
django_bibblio-0.2.dist-info/DESCRIPTION.rst
django_bibblio-0.2.dist-info/METADATA
django_bibblio-0.2.dist-info/RECORD
django_bibblio-0.2.dist-info/WHEEL
django_bibblio-0.2.dist-info/metadata.json
django_bibblio-0.2.dist-info/top_level.txt
example/simpleapp/__init__.py
example/simpleapp/admin.py
example/simpleapp/models.py
example/simpleapp/urls.py
